smartchunk/__init__.py
smartchunk/smartchunking.py
smartchunk-0.1.1.dist-info/LICENSE
smartchunk-0.1.1.dist-info/METADATA
smartchunk-0.1.1.dist-info/WHEEL
smartchunk-0.1.1.dist-info/top_level.txt
smartchunk-0.1.1.dist-info/RECORD
