Metadata-Version: 2.1
Name: smartchunk
Version: 0.1.1
Summary: A PDF chunking Library to Smartly Chunk PDF files
Author: Bishal Bose
Author-email: bishalbose294@gmail.com
Keywords: python,llm,pdf,text chunking,semantic chunking,chunks
Classifier: Development Status :: 1 - Planning
Classifier: Intended Audience :: Developers
Classifier: Programming Language :: Python :: 3
Classifier: Operating System :: Unix
Classifier: Operating System :: MacOS :: MacOS X
Classifier: Operating System :: Microsoft :: Windows
License-File: LICENSE
Requires-Dist: PyMuPDF
Requires-Dist: numpy
Requires-Dist: pandas
Requires-Dist: Unidecode
